aeronet/__init__.py
aeronet/__version__.py
aeronet/converters/__init__.py
aeronet/converters/split.py
aeronet/dataset/__init__.py
aeronet/dataset/coords.py
aeronet/dataset/utils.py
aeronet/dataset/io/__init__.py
aeronet-0.2.5.dist-info/LICENSE
aeronet-0.2.5.dist-info/METADATA
aeronet-0.2.5.dist-info/WHEEL
aeronet-0.2.5.dist-info/top_level.txt
aeronet-0.2.5.dist-info/RECORD
