Metadata-Version: 2.1
Name: aeronet
Version: 0.2.5
Summary: Deep learning with remote sensing data.
Home-page: 
Author: Geoalert
Author-email: hello@geoalert.com
License: MIT
Classifier: License :: OSI Approved :: MIT License
Classifier: Programming Language :: Python
Classifier: Programming Language :: Python :: 3
Classifier: Programming Language :: Python :: 3.6
Classifier: Programming Language :: Python :: Implementation :: CPython
Classifier: Programming Language :: Python :: Implementation :: PyPy
Requires-Python: >=3.6.0
License-File: LICENSE
Provides-Extra: all
Requires-Dist: aeronet-vector ==0.2.5 ; extra == 'all'
Requires-Dist: aeronet-raster ==0.2.5 ; extra == 'all'
Requires-Dist: aeronet-convert ==0.2.5 ; extra == 'all'
Provides-Extra: convert
Requires-Dist: aeronet-convert ==0.2.5 ; extra == 'convert'
Provides-Extra: raster
Requires-Dist: aeronet-raster ==0.2.5 ; extra == 'raster'
Provides-Extra: vector
Requires-Dist: aeronet-vector ==0.2.5 ; extra == 'vector'
